sqlCom/__init__.py
sqlCom-0.1.0.data/data/my_data/data_file
sqlCom-0.1.0.dist-info/DESCRIPTION.rst
sqlCom-0.1.0.dist-info/LICENSE.txt
sqlCom-0.1.0.dist-info/METADATA
sqlCom-0.1.0.dist-info/RECORD
sqlCom-0.1.0.dist-info/WHEEL
sqlCom-0.1.0.dist-info/entry_points.txt
sqlCom-0.1.0.dist-info/metadata.json
sqlCom-0.1.0.dist-info/top_level.txt
