Metadata-Version: 2.0
Name: sqlCom
Version: 0.1.0
Summary: A sample Python Database middleware [MySql, MongoDB, SQLServer]
Home-page: https://chyidl.com/webapp
Author: Yaqing Chyi
Author-email: ChyiYaqing@gmail.com
License: MIT
Keywords: sqlCom setuptools development
Platform: UNKNOWN
Classifier: Development Status :: 3 - Alpha
Classifier: Intended Audience :: Developers
Classifier: Topic :: Software Development :: Build Tools
Classifier: License :: OSI Approved :: MIT License
Classifier: Programming Language :: Python :: 3
Classifier: Programming Language :: Python :: 3.4
Classifier: Programming Language :: Python :: 3.5
Classifier: Programming Language :: Python :: 3.6
Classifier: Programming Language :: Python :: 3.7
Requires-Dist: psutil
Provides-Extra: dev
Requires-Dist: check-manifest; extra == 'dev'
Provides-Extra: test
Requires-Dist: coverage; extra == 'test'
